Flag-0.1.1.dist-info/DESCRIPTION.rst
Flag-0.1.1.dist-info/METADATA
Flag-0.1.1.dist-info/RECORD
Flag-0.1.1.dist-info/WHEEL
Flag-0.1.1.dist-info/metadata.json
Flag-0.1.1.dist-info/top_level.txt
flag/__init__.py
flag/core.py
flag/parser.py
flag/registry.py
flag/utils.py
