Metadata-Version: 1.0
Name: Flag
Version: 0.1.1
Summary: Simple flag library for python
Home-page: http://github.com/danielchatfield/flag
Author: Daniel Chatfield
Author-email: chatfielddaniel@gmail.com
License: UNKNOWN
Platform: UNKNOWN
